roy_on_ray-0.0.1rc0.dist-info/WHEEL
roy_on_ray-0.0.1rc0.dist-info/LICENSE
roy_on_ray-0.0.1rc0.dist-info/top_level.txt
roy_on_ray-0.0.1rc0.dist-info/RECORD
roy_on_ray-0.0.1rc0.dist-info/METADATA
roy_on_ray/roybase.pyx
roy_on_ray/roybase.c
roy_on_ray/roydict.cpython-311-x86_64-linux-gnu.so
roy_on_ray/royset.pyx
roy_on_ray/royset.c
roy_on_ray/roylist.cpython-311-x86_64-linux-gnu.so
roy_on_ray/royremote.py
roy_on_ray/roybase.pxd
roy_on_ray/roybase.cpython-311-x86_64-linux-gnu.so
roy_on_ray/roydict.c
roy_on_ray/royproxy.py
roy_on_ray/roylock.py
roy_on_ray/royset.cpython-311-x86_64-linux-gnu.so
roy_on_ray/roylist.pyx
roy_on_ray/__init__.py
roy_on_ray/roydict.pyx
roy_on_ray/roylist.c
