Metadata-Version: 2.1
Name: roy_on_ray
Version: 0.0.1rc0
Summary: A data structure layer for mutable remote objects on Ray.
Author-email: Seung-seob Lee <seung-seob.lee@yale.edu>
Project-URL: Homepage, https://github.com/Yale-NeRD/roy
Project-URL: Issues, https://github.com/Yale-NeRD/roy/issues
Classifier: Programming Language :: Python :: 3
Classifier: License :: OSI Approved :: Apache Software License
Classifier: Operating System :: OS Independent
Requires-Python: >=3.9
License-File: LICENSE
